mab_forge/__init__.py
mab_forge/_opt.py
mab_forge/_sampler.py
mab_forge-0.1.0.dist-info/LICENSE
mab_forge-0.1.0.dist-info/METADATA
mab_forge-0.1.0.dist-info/WHEEL
mab_forge-0.1.0.dist-info/RECORD
