Metadata-Version: 2.1
Name: mab-forge
Version: 0.1.0
Summary: Toolset for generating Multi-Armed Bandit problems according to a user-defined difficulty
License: MIT
Author: Giovanni Gatti Pinheiro
Author-email: giovanni.gatti.pinheiro@gmail.com
Maintainer: Giovanni Gatti Pinheiro
Maintainer-email: giovanni.gatti.pinheiro@gmail.com
Requires-Python: >=3.9,<4.0
Classifier: Development Status :: 5 - Production/Stable
Classifier: License :: OSI Approved :: MIT License
Classifier: Operating System :: OS Independent
Classifier: Programming Language :: Python :: 3
Classifier: Programming Language :: Python :: 3.9
Classifier: Programming Language :: Python :: 3.10
Classifier: Programming Language :: Python :: 3.11
Classifier: Programming Language :: Python :: 3.12
Classifier: Programming Language :: Python :: 3.13
Classifier: Topic :: Scientific/Engineering
Classifier: Topic :: Software Development :: Libraries :: Python Modules
Requires-Dist: numpy (>=2.0.0,<3.0.0)
Requires-Dist: scipy (>=1.15.0,<2.0.0)
